train_generated_data_ml/LICENSE
train_generated_data_ml/README.MD
train_generated_data_ml/__init__.py
train_generated_data_ml/requirements.txt
train_generated_data_ml/thirdparty.json
train_generated_data_ml/train_generated_data_ml.py
train_generated_data_ml-0.11.dist-info/LICENSE.rst
train_generated_data_ml-0.11.dist-info/METADATA
train_generated_data_ml-0.11.dist-info/WHEEL
train_generated_data_ml-0.11.dist-info/top_level.txt
train_generated_data_ml-0.11.dist-info/RECORD
